setup.py
mo_distributions/Binomialdistribution.py
mo_distributions/Gaussiandistribution.py
mo_distributions/Generaldistribution.py
mo_distributions/__init__.py
mo_distributions.egg-info/PKG-INFO
mo_distributions.egg-info/SOURCES.txt
mo_distributions.egg-info/dependency_links.txt
mo_distributions.egg-info/not-zip-safe
mo_distributions.egg-info/top_level.txt