Metadata-Version: 1.0
Name: mo-distributions
Version: 0.1
Summary: Binomial and Gaussian distributions
Home-page: UNKNOWN
Author: Mojeed Akande
Author-email: mojeeedakande@gmail.com
License: UNKNOWN
Platform: UNKNOWN
